gmailscheduler/__init__.py
gmailscheduler/google_calendar.py
gmailscheduler/participant.py
gmailscheduler/scheduler.py
gmailscheduler-0.1.3.dist-info/METADATA
gmailscheduler-0.1.3.dist-info/WHEEL
gmailscheduler-0.1.3.dist-info/RECORD
